pyfactx/AllowanceChargeReasonCode.py
pyfactx/BinaryObject.py
pyfactx/CreditorFinancialAccount.py
pyfactx/CreditorFinancialInstitution.py
pyfactx/DebtorFinancialAccount.py
pyfactx/DocumentLineDocument.py
pyfactx/DocumentTypeCode.py
pyfactx/ExchangedDocument.py
pyfactx/ExchangedDocumentContext.py
pyfactx/FacturXData.py
pyfactx/FacturXGenerator.py
pyfactx/HeaderTradeAgreement.py
pyfactx/HeaderTradeDelivery.py
pyfactx/HeaderTradeSettlement.py
pyfactx/Indicator.py
pyfactx/InvoiceProfile.py
pyfactx/InvoiceTypeCode.py
pyfactx/LegalOrganization.py
pyfactx/LineTradeAgreement.py
pyfactx/LineTradeDelivery.py
pyfactx/LineTradeSettlement.py
pyfactx/Note.py
pyfactx/PaymentMeansCode.py
pyfactx/ProcuringProject.py
pyfactx/ProductCharacteristic.py
pyfactx/ProductClassification.py
pyfactx/ReferencedDocument.py
pyfactx/SpecifiedPeriod.py
pyfactx/SupplyChainEvent.py
pyfactx/SupplyChainTradeLineItem.py
pyfactx/SupplyChainTradeTransaction.py
pyfactx/TaxCategoryCode.py
pyfactx/TaxTypeCode.py
pyfactx/TimeReferenceCode.py
pyfactx/TradeAccountingAccount.py
pyfactx/TradeAddress.py
pyfactx/TradeAllowanceCharge.py
pyfactx/TradeContact.py
pyfactx/TradeCountry.py
pyfactx/TradeParty.py
pyfactx/TradePaymentTerms.py
pyfactx/TradePrice.py
pyfactx/TradeProduct.py
pyfactx/TradeSettlementFinancialCard.py
pyfactx/TradeSettlementHeaderMonetarySummation.py
pyfactx/TradeSettlementLineMonetarySummation.py
pyfactx/TradeSettlementPaymentMeans.py
pyfactx/TradeTax.py
pyfactx/UnitCode.py
pyfactx/UniversalCommunication.py
pyfactx/VATExemptionReasonCode.py
pyfactx/XMLBaseModel.py
pyfactx/__init__.py
pyfactx/namespaces.py
pyfactx/resources/0_minimum/Factur-X_1.07.2_MINIMUM.sch
pyfactx/resources/0_minimum/Factur-X_1.07.2_MINIMUM.xsd
pyfactx/resources/0_minimum/Factur-X_1.07.2_MINIMUM_codedb.xml
pyfactx/resources/0_minimum/Factur-X_1.07.2_MINIMUM_urn_un_unece_uncefact_data_standard_QualifiedDataType_100.xsd
pyfactx-0.7.0.dist-info/licenses/LICENSE
pyfactx-0.7.0.dist-info/METADATA
pyfactx-0.7.0.dist-info/WHEEL
pyfactx-0.7.0.dist-info/top_level.txt
pyfactx-0.7.0.dist-info/RECORD
