Metadata-Version: 2.4
Name: pyfactx
Version: 0.7.0
Summary: Python package using Pydantic models to generate FacturX-compliant documents
Author-email: Vincent Artur <6145191+vartur@users.noreply.github.com>
License-Expression: MIT
Project-URL: Repository, https://github.com/vartur/pyfactx
Keywords: factur-x,invoicing,EN16931,e-invoicing,xml
Classifier: Development Status :: 4 - Beta
Classifier: Intended Audience :: Developers
Classifier: Topic :: Office/Business :: Financial :: Accounting
Classifier: Programming Language :: Python :: 3
Classifier: Programming Language :: Python :: 3.12
Classifier: Programming Language :: Python :: 3.13
Classifier: Programming Language :: Python :: 3.14
Requires-Python: >=3.12
License-File: LICENSE
Requires-Dist: pydantic<3.0,>=2.11.4
Requires-Dist: lxml<7.0,>=6.0.1
Requires-Dist: saxonche<13.0,>=12.8.0
Dynamic: license-file
